easycache.py
easycache-0.1.5.dist-info/DESCRIPTION.rst
easycache-0.1.5.dist-info/METADATA
easycache-0.1.5.dist-info/RECORD
easycache-0.1.5.dist-info/WHEEL
easycache-0.1.5.dist-info/metadata.json
easycache-0.1.5.dist-info/top_level.txt
