Metadata-Version: 2.0
Name: easycache
Version: 0.1.5
Summary: Implementation of a simple persistent value and function cache.
Home-page: https://bitbucket.org/GreedyUser/easycache
Author: Jeff Ward
Author-email: UNKNOWN
License: Apache License, Version 2.0
Platform: UNKNOWN
Classifier: Development Status :: 3 - Alpha
Classifier: Intended Audience :: Developers
Classifier: License :: OSI Approved :: Apache Software License
Classifier: Operating System :: OS Independent
Classifier: Topic :: Utilities
